iruff/__main__.py
iruff-0.1.0.dist-info/METADATA
iruff-0.1.0.dist-info/WHEEL
iruff-0.1.0.dist-info/entry_points.txt
iruff-0.1.0.dist-info/top_level.txt
iruff-0.1.0.dist-info/RECORD
