Metadata-Version: 2.4
Name: iruff
Version: 0.1.0
Summary: A small wrapper CLI for ruff that sorts imports and formats Python code in one command.
Requires-Python: >=3.12
Requires-Dist: ruff>=0.14.10
